Metadata-Version: 2.1
Name: awd
Version: 1.3.2
Summary: a window director;
Home-page: https://github.com/cykerway/awd
Author: Cyker Way
Author-email: cykerway@example.com
License: UNKNOWN
Project-URL: Bug Reports, https://github.com/cykerway/awd/issues
Project-URL: Source, https://github.com/cykerway/awd/
Keywords: window layout
Platform: UNKNOWN
Classifier: Development Status :: 4 - Beta
Classifier: Intended Audience :: End Users/Desktop
Classifier: Topic :: Desktop Environment
Classifier: License :: OSI Approved :: GNU General Public License v3 (GPLv3)
Classifier: Programming Language :: Python :: 3.6
Classifier: Programming Language :: Python :: 3.7
